pumpdotfun/__init__.py
pumpdotfun/common.py
pumpdotfun/consts.py
pumpdotfun/utils.py
pumpdotfun-0.4.0.dist-info/licenses/LICENSE
pumpdotfun-0.4.0.dist-info/METADATA
pumpdotfun-0.4.0.dist-info/WHEEL
pumpdotfun-0.4.0.dist-info/top_level.txt
pumpdotfun-0.4.0.dist-info/RECORD
