Metadata-Version: 2.4
Name: pumpdotfun
Version: 0.4.0
Summary: pump.fun frontend API Wrapper for Python
Home-page: https://github.com/izzulafifteam/py-python.git
Author: Melvin Luis
Author-email: whappiness183@gmail.com
License: MIT
Project-URL: Source, https://github.com/izzulafifteam/pumpdotfun
Project-URL: Documentation, https://frontend-api.pump.fun/api
Classifier: Programming Language :: Python :: 3
Classifier: License :: OSI Approved :: MIT License
Classifier: Operating System :: OS Independent
License-File: LICENSE
Requires-Dist: requests==2.31.0
Requires-Dist: aiogram==3.20.0
Dynamic: author
Dynamic: author-email
Dynamic: classifier
Dynamic: description
Dynamic: description-content-type
Dynamic: home-page
Dynamic: license
Dynamic: license-file
Dynamic: project-url
Dynamic: requires-dist
Dynamic: summary
